CHANGES
LICENSE
MANIFEST.in
Makefile
README.md
README.rst
dev-requirements.txt
discover.py
setup.cfg
setup.py
py_discover.egg-info/PKG-INFO
py_discover.egg-info/SOURCES.txt
py_discover.egg-info/dependency_links.txt
py_discover.egg-info/requires.txt
py_discover.egg-info/top_level.txt
tests/__init__.py
tests/test_pydiscover.py