Metadata-Version: 1.1
Name: py-discover
Version: 0.1.0
Summary: Discover nodes in different Cloud providers
Home-page: https://github.com/nir0s/py-discover
Author: Nir Cohen
Author-email: nir36g@gmail.com
License: Apache License, Version 2.0
Platform: All
Classifier: Development Status :: 3 - Alpha
Classifier: Intended Audience :: Developers
Classifier: Intended Audience :: System Administrators
Classifier: License :: OSI Approved :: Apache Software License
Classifier: Operating System :: POSIX :: Linux
Classifier: Programming Language :: Python :: 2
Classifier: Programming Language :: Python :: 2.7
Classifier: Programming Language :: Python :: 3
Classifier: Programming Language :: Python :: 3.4
Classifier: Programming Language :: Python :: 3.5
Classifier: Programming Language :: Python :: 3.6
Classifier: Topic :: Software Development :: Libraries :: Python Modules
Classifier: Topic :: System :: Operating System
